typed_diskcache/__init__.py
typed_diskcache/exception.py
typed_diskcache/model.py
typed_diskcache/py.typed
typed_diskcache/core/__init__.py
typed_diskcache/core/const.py
typed_diskcache/core/context.py
typed_diskcache/core/types.py
typed_diskcache/database/__init__.py
typed_diskcache/database/connect.py
typed_diskcache/database/connection.py
typed_diskcache/database/model.py
typed_diskcache/database/revision/000_init.py
typed_diskcache/database/revision/__init__.py
typed_diskcache/implement/__init__.py
typed_diskcache/implement/cache/__init__.py
typed_diskcache/implement/cache/utils.py
typed_diskcache/implement/cache/default/__init__.py
typed_diskcache/implement/cache/default/main.py
typed_diskcache/implement/cache/default/utils.py
typed_diskcache/implement/cache/fanout/__init__.py
typed_diskcache/implement/cache/fanout/main.py
typed_diskcache/implement/cache/fanout/utils.py
typed_diskcache/implement/disk/__init__.py
typed_diskcache/implement/disk/main.py
typed_diskcache/implement/disk/utils.py
typed_diskcache/implement/sync/__init__.py
typed_diskcache/implement/sync/lock.py
typed_diskcache/implement/sync/semaphore.py
typed_diskcache/interface/__init__.py
typed_diskcache/interface/cache.py
typed_diskcache/interface/disk.py
typed_diskcache/interface/sync.py
typed_diskcache/log/__init__.py
typed_diskcache/log/log.toml
typed_diskcache/log/log_format.py
typed_diskcache/log/main.py
typed_diskcache/utils/__init__.py
typed_diskcache/utils/dependency.py
typed_diskcache/utils/deque.py
typed_diskcache/utils/memo.py
typed_diskcache/utils/rename.py
typed_diskcache-0.6.2.dist-info/METADATA
typed_diskcache-0.6.2.dist-info/WHEEL
typed_diskcache-0.6.2.dist-info/licenses/LICENSE
typed_diskcache-0.6.2.dist-info/RECORD
