Metadata-Version: 2.4
Name: typed-diskcache
Version: 0.6.2
Summary: Disk and file backed persistent cache.
Project-URL: Documentation, https://typed-diskcache.readthedocs.io/
Project-URL: Repository, https://github.com/phi-friday/typed-diskcache
Author-email: phi <phi.friday@gmail.com>
License:                                  Apache License
License-File: LICENSE
Classifier: Development Status :: 4 - Beta
Classifier: Framework :: AsyncIO
Classifier: License :: OSI Approved :: Apache Software License
Classifier: Programming Language :: Python
Classifier: Programming Language :: Python :: 3
Classifier: Programming Language :: Python :: 3.10
Classifier: Programming Language :: Python :: 3.11
Classifier: Programming Language :: Python :: 3.12
Classifier: Programming Language :: Python :: 3.13
Classifier: Programming Language :: Python :: 3.14
Classifier: Programming Language :: Python :: Free Threading :: 1 - Unstable
Classifier: Programming Language :: Python :: Implementation :: CPython
Requires-Python: >=3.10
Requires-Dist: cloudpickle>=3.1.0
Requires-Dist: pydantic>=2
Requires-Dist: sqlalchemy-utils
Requires-Dist: sqlalchemy>=2.0.13
Requires-Dist: tomli; python_version < '3.11'
Requires-Dist: typing-extensions>=4.10.0
Provides-Extra: asyncio
Requires-Dist: aiosqlite; extra == 'asyncio'
Requires-Dist: anyio>=4; extra == 'asyncio'
Requires-Dist: sqlalchemy[asyncio]>=2; extra == 'asyncio'
